glazing/__init__.py
glazing/__version__.py
glazing/base.py
glazing/downloader.py
glazing/initialize.py
glazing/search.py
glazing/symbols.py
glazing/types.py
glazing/cli/__init__.py
glazing/cli/convert.py
glazing/cli/download.py
glazing/cli/search.py
glazing/cli/xref.py
glazing/framenet/__init__.py
glazing/framenet/converter.py
glazing/framenet/loader.py
glazing/framenet/models.py
glazing/framenet/search.py
glazing/framenet/symbol_parser.py
glazing/framenet/types.py
glazing/propbank/__init__.py
glazing/propbank/converter.py
glazing/propbank/loader.py
glazing/propbank/models.py
glazing/propbank/search.py
glazing/propbank/symbol_parser.py
glazing/propbank/types.py
glazing/references/__init__.py
glazing/references/extractor.py
glazing/references/index.py
glazing/references/mapper.py
glazing/references/models.py
glazing/references/resolver.py
glazing/syntax/__init__.py
glazing/syntax/models.py
glazing/syntax/parser.py
glazing/utils/__init__.py
glazing/utils/cache.py
glazing/utils/fuzzy_match.py
glazing/utils/ranking.py
glazing/utils/special_cases.py
glazing/utils/validators.py
glazing/utils/xml_parser.py
glazing/verbnet/__init__.py
glazing/verbnet/converter.py
glazing/verbnet/gl_models.py
glazing/verbnet/inheritance.py
glazing/verbnet/loader.py
glazing/verbnet/models.py
glazing/verbnet/search.py
glazing/verbnet/symbol_parser.py
glazing/verbnet/types.py
glazing/wordnet/__init__.py
glazing/wordnet/converter.py
glazing/wordnet/loader.py
glazing/wordnet/models.py
glazing/wordnet/morphy.py
glazing/wordnet/relations.py
glazing/wordnet/search.py
glazing/wordnet/symbol_parser.py
glazing/wordnet/types.py
glazing-0.2.0.dist-info/licenses/LICENSE
glazing-0.2.0.dist-info/METADATA
glazing-0.2.0.dist-info/WHEEL
glazing-0.2.0.dist-info/entry_points.txt
glazing-0.2.0.dist-info/top_level.txt
glazing-0.2.0.dist-info/RECORD
