Metadata-Version: 2.4
Name: glazing
Version: 0.2.0
Summary: Unified data models and interfaces for syntactic and semantic frame ontologies
Author-email: Aaron Steven White <aaron.white@rochester.edu>
License: MIT
Project-URL: Homepage, https://github.com/aaronstevenwhite/glazing
Project-URL: Bug Reports, https://github.com/aaronstevenwhite/glazing/issues
Project-URL: Source, https://github.com/aaronstevenwhite/glazing
Project-URL: Documentation, https://glazing.readthedocs.io
Keywords: nlp,linguistics,framenet,propbank,verbnet,wordnet,semantics,lexicon
Classifier: Development Status :: 3 - Alpha
Classifier: Intended Audience :: Science/Research
Classifier: License :: OSI Approved :: MIT License
Classifier: Programming Language :: Python :: 3
Classifier: Programming Language :: Python :: 3.13
Classifier: Topic :: Scientific/Engineering :: Artificial Intelligence
Classifier: Topic :: Text Processing :: Linguistic
Classifier: Typing :: Typed
Requires-Python: >=3.13
License-File: LICENSE
Requires-Dist: pydantic>=2.5.0
Requires-Dist: typing-extensions>=4.9.0
Requires-Dist: python-dateutil>=2.8.2
Requires-Dist: lxml>=5.0.0
Requires-Dist: click>=8.0.0
Requires-Dist: requests>=2.25.0
Requires-Dist: tqdm>=4.60.0
Requires-Dist: rich>=13.0.0
Requires-Dist: python-Levenshtein>=0.20.0
Provides-Extra: dev
Requires-Dist: ruff>=0.1.9; extra == "dev"
Requires-Dist: mypy>=1.8.0; extra == "dev"
Requires-Dist: pytest>=7.4.3; extra == "dev"
Requires-Dist: pytest-cov>=4.1.0; extra == "dev"
Requires-Dist: pytest-asyncio>=0.21.1; extra == "dev"
Requires-Dist: pre-commit>=3.6.0; extra == "dev"
Requires-Dist: lxml-stubs>=0.5.0; extra == "dev"
Requires-Dist: types-requests>=2.25.0; extra == "dev"
Requires-Dist: types-tqdm>=4.60.0; extra == "dev"
Requires-Dist: types-click>=7.1.0; extra == "dev"
Provides-Extra: docs
Requires-Dist: mkdocs>=1.5.3; extra == "docs"
Requires-Dist: mkdocs-material>=9.5.3; extra == "docs"
Requires-Dist: mkdocstrings[python]>=0.24.0; extra == "docs"
Requires-Dist: griffe-pydantic>=1.0.0; extra == "docs"
Requires-Dist: pymdown-extensions>=10.7; extra == "docs"
Dynamic: license-file
